{
  "$schema": "https://developer.microsoft.com/json-schemas/fabric/item/report/definition/visualContainer/2.2.0/schema.json",
  "name": "f4622f04fa124da6ad37",
  "position": {
    "x": 796.896099413186,
    "y": 182.92026234035208,
    "z": 5000,
    "height": 229.04798066965824,
    "width": 437.41801863997233,
    "tabOrder": 5000
  },
  "visual": {
    "visualType": "barChart",
    "query": {
      "queryState": {
        "Category": {
          "projections": [
            {
              "field": {
                "Column": {
                  "Expression": {
                    "SourceRef": {
                      "Entity": "public dim_brand"
                    }
                  },
                  "Property": "brand_name"
                }
              },
              "queryRef": "public dim_brand.brand_name",
              "nativeQueryRef": "brand_name",
              "active": true
            }
          ]
        },
        "Y": {
          "projections": [
            {
              "field": {
                "Measure": {
                  "Expression": {
                    "SourceRef": {
                      "Entity": "public bridge_product_size"
                    }
                  },
                  "Property": "Total Products"
                }
              },
              "queryRef": "public bridge_product_size.Total Products",
              "nativeQueryRef": "Total Products"
            }
          ]
        }
      },
      "sortDefinition": {
        "sort": [
          {
            "field": {
              "Measure": {
                "Expression": {
                  "SourceRef": {
                    "Entity": "public bridge_product_size"
                  }
                },
                "Property": "Total Products"
              }
            },
            "direction": "Descending"
          }
        ],
        "isDefaultSort": true
      }
    },
    "visualContainerObjects": {
      "background": [
        {
          "properties": {
            "color": {
              "solid": {
                "color": {
                  "expr": {
                    "ThemeDataColor": {
                      "ColorId": 2,
                      "Percent": 0.6
                    }
                  }
                }
              }
            }
          }
        }
      ],
      "border": [
        {
          "properties": {
            "show": {
              "expr": {
                "Literal": {
                  "Value": "true"
                }
              }
            },
            "radius": {
              "expr": {
                "Literal": {
                  "Value": "13D"
                }
              }
            },
            "color": {
              "solid": {
                "color": {
                  "expr": {
                    "ThemeDataColor": {
                      "ColorId": 2,
                      "Percent": -0.5
                    }
                  }
                }
              }
            }
          }
        }
      ]
    },
    "drillFilterOtherVisuals": true
  },
  "filterConfig": {
    "filters": [
      {
        "name": "737820a684014e781afa",
        "ordinal": 0,
        "field": {
          "Column": {
            "Expression": {
              "SourceRef": {
                "Entity": "public dim_brand"
              }
            },
            "Property": "brand_name"
          }
        },
        "type": "TopN",
        "filter": {
          "Version": 2,
          "From": [
            {
              "Name": "subquery",
              "Expression": {
                "Subquery": {
                  "Query": {
                    "Version": 2,
                    "From": [
                      {
                        "Name": "p",
                        "Entity": "public dim_brand",
                        "Type": 0
                      },
                      {
                        "Name": "p1",
                        "Entity": "public bridge_product_size",
                        "Type": 0
                      }
                    ],
                    "Select": [
                      {
                        "Column": {
                          "Expression": {
                            "SourceRef": {
                              "Source": "p"
                            }
                          },
                          "Property": "brand_name"
                        },
                        "Name": "field"
                      }
                    ],
                    "OrderBy": [
                      {
                        "Direction": 2,
                        "Expression": {
                          "Measure": {
                            "Expression": {
                              "SourceRef": {
                                "Source": "p1"
                              }
                            },
                            "Property": "Total Products"
                          }
                        }
                      }
                    ],
                    "Top": 10
                  }
                }
              },
              "Type": 2
            },
            {
              "Name": "p",
              "Entity": "public dim_brand",
              "Type": 0
            }
          ],
          "Where": [
            {
              "Condition": {
                "In": {
                  "Expressions": [
                    {
                      "Column": {
                        "Expression": {
                          "SourceRef": {
                            "Source": "p"
                          }
                        },
                        "Property": "brand_name"
                      }
                    }
                  ],
                  "Table": {
                    "SourceRef": {
                      "Source": "subquery"
                    }
                  }
                }
              }
            }
          ]
        }
      },
      {
        "name": "4843d18808fcaebfeeed",
        "ordinal": 1,
        "field": {
          "Measure": {
            "Expression": {
              "SourceRef": {
                "Entity": "public bridge_product_size"
              }
            },
            "Property": "Total Products"
          }
        },
        "type": "Advanced"
      }
    ],
    "filterSortOrder": "Custom"
  }
}